tinyik/__init__.py
tinyik/component.py
tinyik/core.py
tinyik/optimizer.py
tinyik/solver.py
tinyik/visualizer.py
tinyik-2.2.0.dist-info/LICENSE
tinyik-2.2.0.dist-info/WHEEL
tinyik-2.2.0.dist-info/METADATA
tinyik-2.2.0.dist-info/RECORD
