Metadata-Version: 2.1
Name: tinyik
Version: 2.2.0
Summary: A tiny inverse kinematics solver
Home-page: https://github.com/lanius/tinyik
License: MIT
Author: lanius
Author-email: lanius@nirvake.org
Requires-Python: >=3.5,<4.0
Classifier: License :: OSI Approved :: MIT License
Classifier: Programming Language :: Python :: 3
Classifier: Programming Language :: Python :: 3.5
Classifier: Programming Language :: Python :: 3.6
Classifier: Programming Language :: Python :: 3.7
Classifier: Programming Language :: Python :: 3.8
Provides-Extra: viz
Requires-Dist: autograd
Requires-Dist: open3d (>=0.9.0,<0.10.0); extra == "viz"
Requires-Dist: scipy
Project-URL: Repository, https://github.com/lanius/tinyik
